{   "fish": [
        {
            "name": "Trout",
            "strength": 3,
            "value": 10
        }, 
        {
            "name": "Brass",
            "strength": 5,
            "value": 20
        }, 
        {
            "name": "Fish1",
            "strength": 10,
            "value": 40
        },
        {
            "name": "Fish2",
            "strength": 15,
            "value": 60
        },
        {
            "name": "Fish3",
            "strength": 18,
            "value": 75
        },
        {
            "name": "Fish4",
            "strength": 20,
            "value": 100
        }
    ]
}
